code2flow_visualizer-0.8.6.dist-info/licenses/LICENSE
config/__init__.py
config/settings.py
core/__init__.py
core/flow.py
core/tracer.py
decorators/__init__.py
decorators/visualize.py
exporters/__init__.py
exporters/graphviz_exporter.py
exporters/image_exporter.py
exporters/mermaid_exporter.py
jupyter/__init__.py
jupyter/notebook_integration.py
utils/__init__.py
visualizer/__init__.py
visualizer/flow_visualizer.py
code2flow_visualizer-0.8.6.dist-info/METADATA
code2flow_visualizer-0.8.6.dist-info/WHEEL
code2flow_visualizer-0.8.6.dist-info/top_level.txt
code2flow_visualizer-0.8.6.dist-info/RECORD
