Metadata-Version: 2.4
Name: code2flow-visualizer
Version: 0.8.6
Summary: Real-Time Code Execution Visualizer for Python
Home-page: https://github.com/Aryan0854/code2flow-visualizer
Author: Aryan Mishra
Author-email: aryanmishra.dev@gmail.com
Project-URL: Repository, https://github.com/Aryan0854/code2flow-visualizer
Project-URL: Bug Tracker, https://github.com/Aryan0854/code2flow-visualizer/issues
Project-URL: Documentation, https://github.com/Aryan0854/code2flow-visualizer#readme
Keywords: debugging visualization flowchart code-analysis
Classifier: Development Status :: 3 - Alpha
Classifier: Intended Audience :: Developers
Classifier: License :: OSI Approved :: MIT License
Classifier: Programming Language :: Python :: 3
Classifier: Programming Language :: Python :: 3.8
Classifier: Programming Language :: Python :: 3.9
Classifier: Programming Language :: Python :: 3.10
Classifier: Programming Language :: Python :: 3.11
Classifier: Programming Language :: Python :: 3.12
Classifier: Topic :: Software Development :: Debuggers
Classifier: Topic :: Scientific/Engineering :: Visualization
Requires-Python: >=3.8
License-File: LICENSE
Requires-Dist: graphviz>=0.20.0
Requires-Dist: jupyter>=1.0.0
Requires-Dist: ipython>=8.0.0
Requires-Dist: matplotlib>=3.5.0
Requires-Dist: networkx>=2.8.0
Requires-Dist: pydot>=1.4.0
Requires-Dist: ast-decompiler>=0.8.0
Provides-Extra: dev
Requires-Dist: pytest>=7.0.0; extra == "dev"
Requires-Dist: pytest-cov>=4.0.0; extra == "dev"
Requires-Dist: black>=22.0.0; extra == "dev"
Requires-Dist: flake8>=5.0.0; extra == "dev"
Requires-Dist: mypy>=1.0.0; extra == "dev"
Requires-Dist: jupyter-notebook>=6.4.0; extra == "dev"
Provides-Extra: mermaid
Requires-Dist: mermaid-py>=0.1.0; extra == "mermaid"
Dynamic: author
Dynamic: author-email
Dynamic: classifier
Dynamic: description
Dynamic: description-content-type
Dynamic: home-page
Dynamic: keywords
Dynamic: license-file
Dynamic: project-url
Dynamic: provides-extra
Dynamic: requires-dist
Dynamic: requires-python
Dynamic: summary
